{
    "application_data": [
        {
            "code": 1744,
            "name": "Admiralty Primary School",
            "availableVacancies": 210,
            "phase2aVacancies": 75,
            "phase2aApplicants": 32,
            "phase2aBallotStatus": 0,
            "phase2aBallotChance": -1,
            "phase2bVacancies": 34,
            "phase2bApplicants": 37,
            "phase2bBallotStatus": 4,
            "phase2bBallotChance": 0.4,
            "phase2cVacancies": 70,
            "phase2cApplicants": 109,
            "phase2cBallotStatus": 1,
            "phase2cBallotChance": 0.8045977011,
            "phase2csVacancies": 0,
            "phase2csApplicants": 0,
            "phase2csBallotStatus": 7,
            "phase2csBallotChance": -1
        },
        {
            "code": 1738,
            "name": "Ahmad Ibrahim Primary School",
            "availableVacancies": 220,
            "phase2aVacancies": 106,
            "phase2aApplicants": 10,
            "phase2aBallotStatus": 0,
            "phase2aBallotChance": -1,
            "phase2bVacancies": 52,
            "phase2bApplicants": 0,
            "phase2bBallotStatus": 0,
            "phase2bBallotChance": -1,
            "phase2cVacancies": 157,
            "phase2cApplicants": 27,
            "phase2cBallotStatus": 0,
            "phase2cBallotChance": -1,
            "phase2csVacancies": 130,
            "phase2csApplicants": 15,
            "phase2csBallotStatus": 0,
            "phase2csBallotChance": -1
        },
        {
            "code": 5625,
            "name": "Ai Tong School",
            "availableVacancies": 300,
            "phase2aVacancies": 126,
            "phase2aApplicants": 120,
            "phase2aBallotStatus": 0,
            "phase2aBallotChance": -1,
            "phase2bVacancies": 22,
            "phase2bApplicants": 56,
            "phase2bBallotStatus": 1,
            "phase2bBallotChance": 0.4583333333,
            "phase2cVacancies": 45,
            "phase2cApplicants": 78,
            "phase2cBallotStatus": 1,
            "phase2cBallotChance": 0.6,
            "phase2csVacancies": 0,
            "phase2csApplicants": 0,
            "phase2csBallotStatus": 7,
            "phase2csBallotChance": -1
        },
        {
            "code": 1266,
            "name": "Alexandra Primary School",
            "availableVacancies": 200,
            "phase2aVacancies": 83,
            "phase2aApplicants": 13,
            "phase2aBallotStatus": 0,
            "phase2aBallotChance": -1,
            "phase2bVacancies": 43,
            "phase2bApplicants": 4,
            "phase2bBallotStatus": 0,
            "phase2bBallotChance": -1,
            "phase2cVacancies": 127,
            "phase2cApplicants": 141,
            "phase2cBallotStatus": 3,
            "phase2cBallotChance": 0.6666666667,
            "phase2csVacancies": 0,
            "phase2csApplicants": 0,
            "phase2csBallotStatus": 7,
            "phase2csBallotChance": -1
        },
        {
            "code": 1254,
            "name": "Anchor Green Primary School",
            "availableVacancies": 240,
            "phase2aVacancies": 95,
            "phase2aApplicants": 30,
            "phase2aBallotStatus": 0,
            "phase2aBallotChance": -1,
            "phase2bVacancies": 42,
            "phase2bApplicants": 0,
            "phase2bBallotStatus": 0,
            "phase2bBallotChance": -1,
            "phase2cVacancies": 128,
            "phase2cApplicants": 36,
            "phase2cBallotStatus": 0,
            "phase2cBallotChance": -1,
            "phase2csVacancies": 93,
            "phase2csApplicants": 66,
            "phase2csBallotStatus": 0,
            "phase2csBallotChance": -1
        },
        {
            "code": 1766,
            "name": "Anderson Primary School",
            "availableVacancies": 210,
            "phase2aVacancies": 79,
            "phase2aApplicants": 46,
            "phase2aBallotStatus": 0,
            "phase2aBallotChance": -1,
            "phase2bVacancies": 31,
            "phase2bApplicants": 19,
            "phase2bBallotStatus": 0,
            "phase2bBallotChance": -1,
            "phase2cVacancies": 74,
            "phase2cApplicants": 92,
            "phase2cBallotStatus": 2,
            "phase2cBallotChance": 0.75,
            "phase2csVacancies": 0,
            "phase2csApplicants": 0,
            "phase2csBallotStatus": 7,
            "phase2csBallotChance": -1
        },
        {
            "code": 1150,
            "name": "Ang Mo Kio Primary School",
            "availableVacancies": 150,
            "phase2aVacancies": 58,
            "phase2aApplicants": 33,
            "phase2aBallotStatus": 0,
            "phase2aBallotChance": -1,
            "phase2bVacancies": 28,
            "phase2bApplicants": 0,
            "phase2bBallotStatus": 0,
            "phase2bBallotChance": -1,
            "phase2cVacancies": 85,
            "phase2cApplicants": 29,
            "phase2cBallotStatus": 0,
            "phase2cBallotChance": -1,
            "phase2csVacancies": 56,
            "phase2csApplicants": 15,
            "phase2csBallotStatus": 0,
            "phase2csBallotChance": -1
        },
        {
            "code": 5001,
            "name": "Anglo-Chinese School (Junior)",
            "availableVacancies": 270,
            "phase2aVacancies": 134,
            "phase2aApplicants": 101,
            "phase2aBallotStatus": 0,
            "phase2aBallotChance": -1,
            "phase2bVacancies": 31,
            "phase2bApplicants": 52,
            "phase2bBallotStatus": 1,
            "phase2bBallotChance": 0.7380952381,
            "phase2cVacancies": 62,
            "phase2cApplicants": 79,
            "phase2cBallotStatus": 3,
            "phase2cBallotChance": 0.1428571429,
            "phase2csVacancies": 0,
            "phase2csApplicants": 0,
            "phase2csBallotStatus": 7,
            "phase2csBallotChance": -1
        },
        {
            "code": 5638,
            "name": "Anglo-Chinese School (Primary)",
            "availableVacancies": 240,
            "phase2aVacancies": 124,
            "phase2aApplicants": 106,
            "phase2aBallotStatus": 0,
            "phase2aBallotChance": -1,
            "phase2bVacancies": 26,
            "phase2bApplicants": 51,
            "phase2bBallotStatus": 1,
            "phase2bBallotChance": 0.5531914894,
            "phase2cVacancies": 53,
            "phase2cApplicants": 68,
            "phase2cBallotStatus": 1,
            "phase2cBallotChance": 0.9464285714,
            "phase2csVacancies": 0,
            "phase2csApplicants": 0,
            "phase2csBallotStatus": 7,
            "phase2csBallotChance": -1
        },
        {
            "code": 1268,
            "name": "Angsana Primary School",
            "availableVacancies": 280,
            "phase2aVacancies": 132,
            "phase2aApplicants": 95,
            "phase2aBallotStatus": 0,
            "phase2aBallotChance": -1,
            "phase2bVacancies": 32,
            "phase2bApplicants": 2,
            "phase2bBallotStatus": 0,
            "phase2bBallotChance": -1,
            "phase2cVacancies": 95,
            "phase2cApplicants": 167,
            "phase2cBallotStatus": 1,
            "phase2cBallotChance": 0.59375,
            "phase2csVacancies": 0,
            "phase2csApplicants": 0,
            "phase2csBallotStatus": 7,
            "phase2csBallotChance": -1
        },
        {
            "code": 1249,
            "name": "Beacon Primary School",
            "availableVacancies": 150,
            "phase2aVacancies": 30,
            "phase2aApplicants": 6,
            "phase2aBallotStatus": 0,
            "phase2aBallotChance": -1,
            "phase2bVacancies": 28,
            "phase2bApplicants": 0,
            "phase2bBallotStatus": 0,
            "phase2bBallotChance": -1,
            "phase2cVacancies": 84,
            "phase2cApplicants": 31,
            "phase2cBallotStatus": 0,
            "phase2cBallotChance": -1,
            "phase2csVacancies": 53,
            "phase2csApplicants": 9,
            "phase2csBallotStatus": 0,
            "phase2csBallotChance": -1
        },
        {
            "code": 1230,
            "name": "Bedok Green Primary School",
            "availableVacancies": 210,
            "phase2aVacancies": 94,
            "phase2aApplicants": 11,
            "phase2aBallotStatus": 0,
            "phase2aBallotChance": -1,
            "phase2bVacancies": 48,
            "phase2bApplicants": 0,
            "phase2bBallotStatus": 0,
            "phase2bBallotChance": -1,
            "phase2cVacancies": 143,
            "phase2cApplicants": 27,
            "phase2cBallotStatus": 0,
            "phase2cBallotChance": -1,
            "phase2csVacancies": 116,
            "phase2csApplicants": 36,
            "phase2csBallotStatus": 0,
            "phase2csBallotChance": -1
        },
        {
            "code": 1129,
            "name": "Bendemeer Primary School",
            "availableVacancies": 190,
            "phase2aVacancies": 94,
            "phase2aApplicants": 12,
            "phase2aBallotStatus": 0,
            "phase2aBallotChance": -1,
            "phase2bVacancies": 47,
            "phase2bApplicants": 1,
            "phase2bBallotStatus": 0,
            "phase2bBallotChance": -1,
            "phase2cVacancies": 143,
            "phase2cApplicants": 30,
            "phase2cBallotStatus": 0,
            "phase2cBallotChance": -1,
            "phase2csVacancies": 113,
            "phase2csApplicants": 50,
            "phase2csBallotStatus": 0,
            "phase2csBallotChance": -1
        },
        {
            "code": 1145,
            "name": "Blangah Rise Primary School",
            "availableVacancies": 120,
            "phase2aVacancies": 37,
            "phase2aApplicants": 20,
            "phase2aBallotStatus": 0,
            "phase2aBallotChance": -1,
            "phase2bVacancies": 26,
            "phase2bApplicants": 0,
            "phase2bBallotStatus": 0,
            "phase2bBallotChance": -1,
            "phase2cVacancies": 77,
            "phase2cApplicants": 18,
            "phase2cBallotStatus": 0,
            "phase2cBallotChance": -1,
            "phase2csVacancies": 60,
            "phase2csApplicants": 12,
            "phase2csBallotStatus": 0,
            "phase2csBallotChance": -1
        },
        {
            "code": 1640,
            "name": "Boon Lay Garden Primary School",
            "availableVacancies": 180,
            "phase2aVacancies": 74,
            "phase2aApplicants": 15,
            "phase2aBallotStatus": 0,
            "phase2aBallotChance": -1,
            "phase2bVacancies": 40,
            "phase2bApplicants": 0,
            "phase2bBallotStatus": 0,
            "phase2bBallotChance": -1,
            "phase2cVacancies": 121,
            "phase2cApplicants": 27,
            "phase2cBallotStatus": 0,
            "phase2cBallotChance": -1,
            "phase2csVacancies": 94,
            "phase2csApplicants": 25,
            "phase2csBallotStatus": 0,
            "phase2csBallotChance": -1
        },
        {
            "code": 1020,
            "name": "Bukit Panjang Primary School",
            "availableVacancies": 240,
            "phase2aVacancies": 80,
            "phase2aApplicants": 78,
            "phase2aBallotStatus": 0,
            "phase2aBallotChance": -1,
            "phase2bVacancies": 21,
            "phase2bApplicants": 24,
            "phase2bBallotStatus": 2,
            "phase2bBallotChance": 0.8,
            "phase2cVacancies": 42,
            "phase2cApplicants": 89,
            "phase2cBallotStatus": 1,
            "phase2cBallotChance": 0.5526315789,
            "phase2csVacancies": 0,
            "phase2csApplicants": 0,
            "phase2csBallotStatus": 7,
            "phase2csBallotChance": -1
        },
        {
            "code": 1247,
            "name": "Bukit Timah Primary School",
            "availableVacancies": 180,
            "phase2aVacancies": 56,
            "phase2aApplicants": 7,
            "phase2aBallotStatus": 0,
            "phase2aBallotChance": -1,
            "phase2bVacancies": 36,
            "phase2bApplicants": 1,
            "phase2bBallotStatus": 0,
            "phase2bBallotChance": -1,
            "phase2cVacancies": 111,
            "phase2cApplicants": 71,
            "phase2cBallotStatus": 0,
            "phase2cBallotChance": -1,
            "phase2csVacancies": 40,
            "phase2csApplicants": 66,
            "phase2csBallotStatus": 2,
            "phase2csBallotChance": 0.8947368421
        },
        {
            "code": 1209,
            "name": "Bukit View Primary School",
            "availableVacancies": 320,
            "phase2aVacancies": 198,
            "phase2aApplicants": 17,
            "phase2aBallotStatus": 0,
            "phase2aBallotChance": -1,
            "phase2bVacancies": 80,
            "phase2bApplicants": 0,
            "phase2bBallotStatus": 0,
            "phase2bBallotChance": -1,
            "phase2cVacancies": 242,
            "phase2cApplicants": 27,
            "phase2cBallotStatus": 0,
            "phase2cBallotChance": -1,
            "phase2csVacancies": 215,
            "phase2csApplicants": 127,
            "phase2csBallotStatus": 0,
            "phase2csBallotChance": -1
        },
        {
            "code": 1751,
            "name": "Canberra Primary School",
            "availableVacancies": 240,
            "phase2aVacancies": 100,
            "phase2aApplicants": 16,
            "phase2aBallotStatus": 0,
            "phase2aBallotChance": -1,
            "phase2bVacancies": 48,
            "phase2bApplicants": 22,
            "phase2bBallotStatus": 0,
            "phase2bBallotChance": -1,
            "phase2cVacancies": 122,
            "phase2cApplicants": 131,
            "phase2cBallotStatus": 2,
            "phase2cBallotChance": 0.75,
            "phase2csVacancies": 0,
            "phase2csApplicants": 0,
            "phase2csBallotStatus": 7,
            "phase2csBallotChance": -1
        },
        {
            "code": 5029,
            "name": "Canossa Catholic Primary School",
            "availableVacancies": 120,
            "phase2aVacancies": 12,
            "phase2aApplicants": 3,
            "phase2aBallotStatus": 0,
            "phase2aBallotChance": -1,
            "phase2bVacancies": 23,
            "phase2bApplicants": 19,
            "phase2bBallotStatus": 0,
            "phase2bBallotChance": -1,
            "phase2cVacancies": 50,
            "phase2cApplicants": 56,
            "phase2cBallotStatus": 2,
            "phase2cBallotChance": 1,
            "phase2csVacancies": 0,
            "phase2csApplicants": 0,
            "phase2csBallotStatus": 7,
            "phase2csBallotChance": -1
        },
        {
            "code": 1256,
            "name": "Cantonment Primary School",
            "availableVacancies": 150,
            "phase2aVacancies": 45,
            "phase2aApplicants": 4,
            "phase2aBallotStatus": 0,
            "phase2aBallotChance": -1,
            "phase2bVacancies": 34,
            "phase2bApplicants": 2,
            "phase2bBallotStatus": 0,
            "phase2bBallotChance": -1,
            "phase2cVacancies": 100,
            "phase2cApplicants": 40,
            "phase2cBallotStatus": 0,
            "phase2cBallotChance": -1,
            "phase2csVacancies": 60,
            "phase2csApplicants": 19,
            "phase2csBallotStatus": 0,
            "phase2csBallotChance": -1
        },
        {
            "code": 1771,
            "name": "Casuarina Primary School",
            "availableVacancies": 160,
            "phase2aVacancies": 24,
            "phase2aApplicants": 18,
            "phase2aBallotStatus": 0,
            "phase2aBallotChance": -1,
            "phase2bVacancies": 22,
            "phase2bApplicants": 0,
            "phase2bBallotStatus": 0,
            "phase2bBallotChance": -1,
            "phase2cVacancies": 66,
            "phase2cApplicants": 44,
            "phase2cBallotStatus": 0,
            "phase2cBallotChance": -1,
            "phase2csVacancies": 23,
            "phase2csApplicants": 28,
            "phase2csBallotStatus": 2,
            "phase2csBallotChance": 0.9166666667
        },
        {
            "code": 7102,
            "name": "Catholic High School",
            "availableVacancies": 240,
            "phase2aVacancies": 116,
            "phase2aApplicants": 135,
            "phase2aBallotStatus": 3,
            "phase2aBallotChance": 0.6603773585,
            "phase2bVacancies": 20,
            "phase2bApplicants": 29,
            "phase2bBallotStatus": 1,
            "phase2bBallotChance": 0.8695652174,
            "phase2cVacancies": 40,
            "phase2cApplicants": 52,
            "phase2cBallotStatus": 1,
            "phase2cBallotChance": 0.9090909091,
            "phase2csVacancies": 0,
            "phase2csApplicants": 0,
            "phase2csBallotStatus": 7,
            "phase2csBallotChance": -1
        },
        {
            "code": 1211,
            "name": "Cedar Primary School",
            "availableVacancies": 240,
            "phase2aVacancies": 128,
            "phase2aApplicants": 36,
            "phase2aBallotStatus": 0,
            "phase2aBallotChance": -1,
            "phase2bVacancies": 51,
            "phase2bApplicants": 1,
            "phase2bBallotStatus": 0,
            "phase2bBallotChance": -1,
            "phase2cVacancies": 151,
            "phase2cApplicants": 38,
            "phase2cBallotStatus": 0,
            "phase2cBallotChance": -1,
            "phase2csVacancies": 113,
            "phase2csApplicants": 38,
            "phase2csBallotStatus": 0,
            "phase2csBallotChance": -1
        },
        {
            "code": 1239,
            "name": "Changkat Primary School",
            "availableVacancies": 180,
            "phase2aVacancies": 75,
            "phase2aApplicants": 15,
            "phase2aBallotStatus": 0,
            "phase2aBallotChance": -1,
            "phase2bVacancies": 40,
            "phase2bApplicants": 1,
            "phase2bBallotStatus": 0,
            "phase2bBallotChance": -1,
            "phase2cVacancies": 119,
            "phase2cApplicants": 56,
            "phase2cBallotStatus": 0,
            "phase2cBallotChance": -1,
            "phase2csVacancies": 63,
            "phase2csApplicants": 13,
            "phase2csBallotStatus": 0,
            "phase2csBallotChance": -1
        },
        {
            "code": 5637,
            "name": "CHIJ (Katong) Primary",
            "availableVacancies": 200,
            "phase2aVacancies": 96,
            "phase2aApplicants": 30,
            "phase2aBallotStatus": 0,
            "phase2aBallotChance": -1,
            "phase2bVacancies": 42,
            "phase2bApplicants": 21,
            "phase2bBallotStatus": 0,
            "phase2bBallotChance": -1,
            "phase2cVacancies": 105,
            "phase2cApplicants": 63,
            "phase2cBallotStatus": 0,
            "phase2cBallotChance": -1,
            "phase2csVacancies": 42,
            "phase2csApplicants": 55,
            "phase2csBallotStatus": 3,
            "phase2csBallotChance": 0.75
        },
        {
            "code": 5005,
            "name": "CHIJ (Kellock)",
            "availableVacancies": 200,
            "phase2aVacancies": 93,
            "phase2aApplicants": 12,
            "phase2aBallotStatus": 0,
            "phase2aBallotChance": -1,
            "phase2bVacancies": 47,
            "phase2bApplicants": 14,
            "phase2bBallotStatus": 0,
            "phase2bBallotChance": -1,
            "phase2cVacancies": 128,
            "phase2cApplicants": 49,
            "phase2cBallotStatus": 0,
            "phase2cBallotChance": -1,
            "phase2csVacancies": 79,
            "phase2csApplicants": 22,
            "phase2csBallotStatus": 0,
            "phase2csBallotChance": -1
        },
        {
            "code": 5017,
            "name": "CHIJ Our Lady Of Good Counsel",
            "availableVacancies": 150,
            "phase2aVacancies": 61,
            "phase2aApplicants": 11,
            "phase2aBallotStatus": 0,
            "phase2aBallotChance": -1,
            "phase2bVacancies": 37,
            "phase2bApplicants": 11,
            "phase2bBallotStatus": 0,
            "phase2bBallotChance": -1,
            "phase2cVacancies": 101,
            "phase2cApplicants": 40,
            "phase2cBallotStatus": 0,
            "phase2cBallotChance": -1,
            "phase2csVacancies": 61,
            "phase2csApplicants": 43,
            "phase2csBallotStatus": 0,
            "phase2csBallotChance": -1
        },
        {
            "code": 5007,
            "name": "CHIJ Our Lady Of The Nativity",
            "availableVacancies": 240,
            "phase2aVacancies": 120,
            "phase2aApplicants": 24,
            "phase2aBallotStatus": 0,
            "phase2aBallotChance": -1,
            "phase2bVacancies": 52,
            "phase2bApplicants": 45,
            "phase2bBallotStatus": 0,
            "phase2bBallotChance": -1,
            "phase2cVacancies": 111,
            "phase2cApplicants": 113,
            "phase2cBallotStatus": 4,
            "phase2cBallotChance": 0.6,
            "phase2csVacancies": 0,
            "phase2csApplicants": 0,
            "phase2csBallotStatus": 7,
            "phase2csBallotChance": -1
        },
        {
            "code": 5019,
            "name": "CHIJ Our Lady Queen Of Peace",
            "availableVacancies": 180,
            "phase2aVacancies": 72,
            "phase2aApplicants": 15,
            "phase2aBallotStatus": 0,
            "phase2aBallotChance": -1,
            "phase2bVacancies": 40,
            "phase2bApplicants": 14,
            "phase2bBallotStatus": 0,
            "phase2bBallotChance": -1,
            "phase2cVacancies": 105,
            "phase2cApplicants": 59,
            "phase2cBallotStatus": 0,
            "phase2cBallotChance": -1,
            "phase2csVacancies": 46,
            "phase2csApplicants": 37,
            "phase2csBallotStatus": 0,
            "phase2csBallotChance": -1
        },
        {
            "code": 5004,
            "name": "CHIJ Primary (Toa Payoh)",
            "availableVacancies": 210,
            "phase2aVacancies": 100,
            "phase2aApplicants": 78,
            "phase2aBallotStatus": 0,
            "phase2aBallotChance": -1,
            "phase2bVacancies": 27,
            "phase2bApplicants": 53,
            "phase2bBallotStatus": 1,
            "phase2bBallotChance": 0.9,
            "phase2cVacancies": 55,
            "phase2cApplicants": 69,
            "phase2cBallotStatus": 1,
            "phase2cBallotChance": 0.6153846154,
            "phase2csVacancies": 0,
            "phase2csApplicants": 0,
            "phase2csBallotStatus": 7,
            "phase2csBallotChance": -1
        },
        {
            "code": 7118,
            "name": "CHIJ St. Nicholas Girls' School",
            "availableVacancies": 210,
            "phase2aVacancies": 80,
            "phase2aApplicants": 103,
            "phase2aBallotStatus": 3,
            "phase2aBallotChance": 0.4772727273,
            "phase2bVacancies": 20,
            "phase2bApplicants": 46,
            "phase2bBallotStatus": 1,
            "phase2bBallotChance": 0.5555555556,
            "phase2cVacancies": 40,
            "phase2cApplicants": 84,
            "phase2cBallotStatus": 1,
            "phase2cBallotChance": 0.5555555556,
            "phase2csVacancies": 0,
            "phase2csApplicants": 0,
            "phase2csBallotStatus": 7,
            "phase2csBallotChance": -1
        },
        {
            "code": 5636,
            "name": "Chongfu School",
            "availableVacancies": 300,
            "phase2aVacancies": 118,
            "phase2aApplicants": 73,
            "phase2aBallotStatus": 0,
            "phase2aBallotChance": -1,
            "phase2bVacancies": 35,
            "phase2bApplicants": 53,
            "phase2bBallotStatus": 1,
            "phase2bBallotChance": 0.9459459459,
            "phase2cVacancies": 72,
            "phase2cApplicants": 112,
            "phase2cBallotStatus": 1,
            "phase2cBallotChance": 0.8181818182,
            "phase2csVacancies": 0,
            "phase2csApplicants": 0,
            "phase2csBallotStatus": 7,
            "phase2csBallotChance": -1
        },
        {
            "code": 1203,
            "name": "Chongzheng Primary School",
            "availableVacancies": 180,
            "phase2aVacancies": 60,
            "phase2aApplicants": 41,
            "phase2aBallotStatus": 0,
            "phase2aBallotChance": -1,
            "phase2bVacancies": 26,
            "phase2bApplicants": 7,
            "phase2bBallotStatus": 0,
            "phase2bBallotChance": -1,
            "phase2cVacancies": 72,
            "phase2cApplicants": 84,
            "phase2cBallotStatus": 2,
            "phase2cBallotChance": 0.4444444444,
            "phase2csVacancies": 0,
            "phase2csApplicants": 0,
            "phase2csBallotStatus": 7,
            "phase2csBallotChance": -1
        },
        {
            "code": 1244,
            "name": "Chua Chu Kang Primary School",
            "availableVacancies": 240,
            "phase2aVacancies": 59,
            "phase2aApplicants": 44,
            "phase2aBallotStatus": 0,
            "phase2aBallotChance": -1,
            "phase2bVacancies": 25,
            "phase2bApplicants": 14,
            "phase2bBallotStatus": 0,
            "phase2bBallotChance": -1,
            "phase2cVacancies": 62,
            "phase2cApplicants": 111,
            "phase2cBallotStatus": 1,
            "phase2cBallotChance": 0.5585585586,
            "phase2csVacancies": 0,
            "phase2csApplicants": 0,
            "phase2csBallotStatus": 7,
            "phase2csBallotChance": -1
        },
        {
            "code": 1772,
            "name": "Clementi Primary School",
            "availableVacancies": 280,
            "phase2aVacancies": 165,
            "phase2aApplicants": 13,
            "phase2aBallotStatus": 0,
            "phase2aBallotChance": -1,
            "phase2bVacancies": 71,
            "phase2bApplicants": 0,
            "phase2bBallotStatus": 0,
            "phase2bBallotChance": -1,
            "phase2cVacancies": 214,
            "phase2cApplicants": 51,
            "phase2cBallotStatus": 0,
            "phase2cBallotChance": -1,
            "phase2csVacancies": 163,
            "phase2csApplicants": 103,
            "phase2csBallotStatus": 0,
            "phase2csBallotChance": -1
        },
        {
            "code": 1757,
            "name": "Compassvale Primary School",
            "availableVacancies": 240,
            "phase2aVacancies": 73,
            "phase2aApplicants": 14,
            "phase2aBallotStatus": 0,
            "phase2aBallotChance": -1,
            "phase2bVacancies": 40,
            "phase2bApplicants": 18,
            "phase2bBallotStatus": 0,
            "phase2bBallotChance": -1,
            "phase2cVacancies": 101,
            "phase2cApplicants": 133,
            "phase2cBallotStatus": 1,
            "phase2cBallotChance": 0.9528301887,
            "phase2csVacancies": 0,
            "phase2csApplicants": 0,
            "phase2csBallotStatus": 7,
            "phase2csBallotChance": -1
        },
        {
            "code": 1760,
            "name": "Concord Primary School",
            "availableVacancies": 240,
            "phase2aVacancies": 81,
            "phase2aApplicants": 32,
            "phase2aBallotStatus": 0,
            "phase2aBallotChance": -1,
            "phase2bVacancies": 36,
            "phase2bApplicants": 1,
            "phase2bBallotStatus": 0,
            "phase2bBallotChance": -1,
            "phase2cVacancies": 108,
            "phase2cApplicants": 76,
            "phase2cBallotStatus": 0,
            "phase2cBallotChance": -1,
            "phase2csVacancies": 32,
            "phase2csApplicants": 54,
            "phase2csBallotStatus": 1,
            "phase2csBallotChance": 0.7804878049
        },
        {
            "code": 1132,
            "name": "Corporation Primary School",
            "availableVacancies": 180,
            "phase2aVacancies": 75,
            "phase2aApplicants": 17,
            "phase2aBallotStatus": 0,
            "phase2aBallotChance": -1,
            "phase2bVacancies": 39,
            "phase2bApplicants": 2,
            "phase2bBallotStatus": 0,
            "phase2bBallotChance": -1,
            "phase2cVacancies": 118,
            "phase2cApplicants": 31,
            "phase2cBallotStatus": 0,
            "phase2cBallotChance": -1,
            "phase2csVacancies": 88,
            "phase2csApplicants": 18,
            "phase2csBallotStatus": 0,
            "phase2csBallotChance": -1
        },
        {
            "code": 1102,
            "name": "Damai Primary School",
            "availableVacancies": 150,
            "phase2aVacancies": 41,
            "phase2aApplicants": 13,
            "phase2aBallotStatus": 0,
            "phase2aBallotChance": -1,
            "phase2bVacancies": 29,
            "phase2bApplicants": 1,
            "phase2bBallotStatus": 0,
            "phase2bBallotChance": -1,
            "phase2cVacancies": 87,
            "phase2cApplicants": 22,
            "phase2cBallotStatus": 0,
            "phase2cBallotChance": -1,
            "phase2csVacancies": 65,
            "phase2csApplicants": 18,
            "phase2csBallotStatus": 0,
            "phase2csBallotChance": -1
        },
        {
            "code": 1229,
            "name": "Dazhong Primary School",
            "availableVacancies": 200,
            "phase2aVacancies": 84,
            "phase2aApplicants": 61,
            "phase2aBallotStatus": 0,
            "phase2aBallotChance": -1,
            "phase2bVacancies": 28,
            "phase2bApplicants": 0,
            "phase2bBallotStatus": 0,
            "phase2bBallotChance": -1,
            "phase2cVacancies": 85,
            "phase2cApplicants": 83,
            "phase2cBallotStatus": 0,
            "phase2cBallotChance": -1,
            "phase2csVacancies": 2,
            "phase2csApplicants": 41,
            "phase2csBallotStatus": 1,
            "phase2csBallotChance": 0.07407407407
        },
        {
            "code": 5008,
            "name": "De La Salle School",
            "availableVacancies": 240,
            "phase2aVacancies": 89,
            "phase2aApplicants": 16,
            "phase2aBallotStatus": 0,
            "phase2aBallotChance": -1,
            "phase2bVacancies": 44,
            "phase2bApplicants": 5,
            "phase2bBallotStatus": 0,
            "phase2bBallotChance": -1,
            "phase2cVacancies": 128,
            "phase2cApplicants": 96,
            "phase2cBallotStatus": 0,
            "phase2cBallotChance": -1,
            "phase2csVacancies": 32,
            "phase2csApplicants": 33,
            "phase2csBallotStatus": 3,
            "phase2csBallotChance": 1
        },
        {
            "code": 1755,
            "name": "East Spring Primary School",
            "availableVacancies": 190,
            "phase2aVacancies": 81,
            "phase2aApplicants": 11,
            "phase2aBallotStatus": 0,
            "phase2aBallotChance": -1,
            "phase2bVacancies": 43,
            "phase2bApplicants": 0,
            "phase2bBallotStatus": 0,
            "phase2bBallotChance": -1,
            "phase2cVacancies": 130,
            "phase2cApplicants": 64,
            "phase2cBallotStatus": 0,
            "phase2cBallotChance": -1,
            "phase2csVacancies": 66,
            "phase2csApplicants": 38,
            "phase2csBallotStatus": 0,
            "phase2csBallotChance": -1
        },
        {
            "code": 1769,
            "name": "Edgefield Primary School",
            "availableVacancies": 240,
            "phase2aVacancies": 109,
            "phase2aApplicants": 7,
            "phase2aBallotStatus": 0,
            "phase2aBallotChance": -1,
            "phase2bVacancies": 54,
            "phase2bApplicants": 0,
            "phase2bBallotStatus": 0,
            "phase2bBallotChance": -1,
            "phase2cVacancies": 162,
            "phase2cApplicants": 46,
            "phase2cBallotStatus": 0,
            "phase2cBallotChance": -1,
            "phase2csVacancies": 116,
            "phase2csApplicants": 24,
            "phase2csBallotStatus": 0,
            "phase2csBallotChance": -1
        },
        {
            "code": 1737,
            "name": "Elias Park Primary School",
            "availableVacancies": 160,
            "phase2aVacancies": 23,
            "phase2aApplicants": 22,
            "phase2aBallotStatus": 0,
            "phase2aBallotChance": -1,
            "phase2bVacancies": 20,
            "phase2bApplicants": 0,
            "phase2bBallotStatus": 0,
            "phase2bBallotChance": -1,
            "phase2cVacancies": 61,
            "phase2cApplicants": 101,
            "phase2cBallotStatus": 1,
            "phase2cBallotChance": 0.7093023256,
            "phase2csVacancies": 0,
            "phase2csApplicants": 0,
            "phase2csBallotStatus": 7,
            "phase2csBallotChance": -1
        },
        {
            "code": 1252,
            "name": "Endeavour Primary School",
            "availableVacancies": 240,
            "phase2aVacancies": 122,
            "phase2aApplicants": 6,
            "phase2aBallotStatus": 0,
            "phase2aBallotChance": -1,
            "phase2bVacancies": 59,
            "phase2bApplicants": 1,
            "phase2bBallotStatus": 0,
            "phase2bBallotChance": -1,
            "phase2cVacancies": 175,
            "phase2cApplicants": 53,
            "phase2cBallotStatus": 0,
            "phase2cBallotChance": -1,
            "phase2csVacancies": 122,
            "phase2csApplicants": 25,
            "phase2csBallotStatus": 0,
            "phase2csBallotChance": -1
        },
        {
            "code": 1756,
            "name": "Evergreen Primary School",
            "availableVacancies": 180,
            "phase2aVacancies": 52,
            "phase2aApplicants": 18,
            "phase2aBallotStatus": 0,
            "phase2aBallotChance": -1,
            "phase2bVacancies": 31,
            "phase2bApplicants": 0,
            "phase2bBallotStatus": 0,
            "phase2bBallotChance": -1,
            "phase2cVacancies": 94,
            "phase2cApplicants": 66,
            "phase2cBallotStatus": 0,
            "phase2cBallotChance": -1,
            "phase2csVacancies": 28,
            "phase2csApplicants": 22,
            "phase2csBallotStatus": 0,
            "phase2csBallotChance": -1
        },
        {
            "code": 5020,
            "name": "Fairfield Methodist School (Primary)",
            "availableVacancies": 270,
            "phase2aVacancies": 94,
            "phase2aApplicants": 103,
            "phase2aBallotStatus": 3,
            "phase2aBallotChance": 0.8333333333,
            "phase2bVacancies": 20,
            "phase2bApplicants": 52,
            "phase2bBallotStatus": 1,
            "phase2bBallotChance": 0.7692307692,
            "phase2cVacancies": 40,
            "phase2cApplicants": 66,
            "phase2cBallotStatus": 1,
            "phase2cBallotChance": 0.7843137255,
            "phase2csVacancies": 0,
            "phase2csApplicants": 0,
            "phase2csBallotStatus": 7,
            "phase2csBallotChance": -1
        },
        {
            "code": 1246,
            "name": "Farrer Park Primary School",
            "availableVacancies": 220,
            "phase2aVacancies": 125,
            "phase2aApplicants": 20,
            "phase2aBallotStatus": 0,
            "phase2aBallotChance": -1,
            "phase2bVacancies": 55,
            "phase2bApplicants": 1,
            "phase2bBallotStatus": 0,
            "phase2bBallotChance": -1,
            "phase2cVacancies": 164,
            "phase2cApplicants": 37,
            "phase2cBallotStatus": 0,
            "phase2cBallotChance": -1,
            "phase2csVacancies": 127,
            "phase2csApplicants": 29,
            "phase2csBallotStatus": 0,
            "phase2csBallotChance": -1
        },
        {
            "code": 1657,
            "name": "Fengshan Primary School",
            "availableVacancies": 180,
            "phase2aVacancies": 67,
            "phase2aApplicants": 33,
            "phase2aBallotStatus": 0,
            "phase2aBallotChance": -1,
            "phase2bVacancies": 31,
            "phase2bApplicants": 2,
            "phase2bBallotStatus": 0,
            "phase2bBallotChance": -1,
            "phase2cVacancies": 96,
            "phase2cApplicants": 75,
            "phase2cBallotStatus": 0,
            "phase2cBallotChance": -1,
            "phase2csVacancies": 21,
            "phase2csApplicants": 39,
            "phase2csBallotStatus": 1,
            "phase2csBallotChance": 0.7777777778
        },
        {
            "code": 1272,
            "name": "Fern Green Primary School",
            "availableVacancies": 240,
            "phase2aVacancies": 50,
            "phase2aApplicants": 50,
            "phase2aBallotStatus": 0,
            "phase2aBallotChance": -1,
            "phase2bVacancies": 20,
            "phase2bApplicants": 1,
            "phase2bBallotStatus": 0,
            "phase2bBallotChance": -1,
            "phase2cVacancies": 61,
            "phase2cApplicants": 73,
            "phase2cBallotStatus": 0,
            "phase2cBallotChance": -1,
            "phase2csVacancies": 61,
            "phase2csApplicants": 73,
            "phase2csBallotStatus": 1,
            "phase2csBallotChance": 0.9242424242
        },
        {
            "code": 1177,
            "name": "Fernvale Primary School",
            "availableVacancies": 240,
            "phase2aVacancies": 103,
            "phase2aApplicants": 35,
            "phase2aBallotStatus": 0,
            "phase2aBallotChance": -1,
            "phase2bVacancies": 43,
            "phase2bApplicants": 0,
            "phase2bBallotStatus": 0,
            "phase2bBallotChance": -1,
            "phase2cVacancies": 129,
            "phase2cApplicants": 80,
            "phase2cBallotStatus": 0,
            "phase2cBallotChance": -1,
            "phase2csVacancies": 49,
            "phase2csApplicants": 56,
            "phase2csBallotStatus": 1,
            "phase2csBallotChance": 0.98
        },
        {
            "code": 1610,
            "name": "First Toa Payoh Primary School",
            "availableVacancies": 150,
            "phase2aVacancies": 71,
            "phase2aApplicants": 13,
            "phase2aBallotStatus": 0,
            "phase2aBallotChance": -1,
            "phase2bVacancies": 39,
            "phase2bApplicants": 0,
            "phase2bBallotStatus": 0,
            "phase2bBallotChance": -1,
            "phase2cVacancies": 119,
            "phase2cApplicants": 9,
            "phase2cBallotStatus": 0,
            "phase2cBallotChance": -1,
            "phase2csVacancies": 110,
            "phase2csApplicants": 14,
            "phase2csBallotStatus": 0,
            "phase2csBallotChance": -1
        },
        {
            "code": 1257,
            "name": "Frontier Primary School",
            "availableVacancies": 210,
            "phase2aVacancies": 81,
            "phase2aApplicants": 88,
            "phase2aBallotStatus": 1,
            "phase2aBallotChance": 0.3333333333,
            "phase2bVacancies": 20,
            "phase2bApplicants": 13,
            "phase2bBallotStatus": 0,
            "phase2bBallotChance": -1,
            "phase2cVacancies": 48,
            "phase2cApplicants": 63,
            "phase2cBallotStatus": 1,
            "phase2cBallotChance": 0.375,
            "phase2csVacancies": 0,
            "phase2csApplicants": 0,
            "phase2csBallotStatus": 7,
            "phase2csBallotChance": -1
        },
        {
            "code": 1208,
            "name": "Fuchun Primary School",
            "availableVacancies": 180,
            "phase2aVacancies": 62,
            "phase2aApplicants": 27,
            "phase2aBallotStatus": 0,
            "phase2aBallotChance": -1,
            "phase2bVacancies": 32,
            "phase2bApplicants": 1,
            "phase2bBallotStatus": 0,
            "phase2bBallotChance": -1,
            "phase2cVacancies": 95,
            "phase2cApplicants": 45,
            "phase2cBallotStatus": 0,
            "phase2cBallotChance": -1,
            "phase2csVacancies": 50,
            "phase2csApplicants": 4,
            "phase2csBallotStatus": 0,
            "phase2csBallotChance": -1
        },
        {
            "code": 1107,
            "name": "Fuhua Primary School",
            "availableVacancies": 220,
            "phase2aVacancies": 99,
            "phase2aApplicants": 30,
            "phase2aBallotStatus": 0,
            "phase2aBallotChance": -1,
            "phase2bVacancies": 43,
            "phase2bApplicants": 2,
            "phase2bBallotStatus": 0,
            "phase2bBallotChance": -1,
            "phase2cVacancies": 128,
            "phase2cApplicants": 54,
            "phase2cBallotStatus": 0,
            "phase2cBallotChance": -1,
            "phase2csVacancies": 74,
            "phase2csApplicants": 31,
            "phase2csBallotStatus": 0,
            "phase2csBallotChance": -1
        },
        {
            "code": 1221,
            "name": "Gan Eng Seng Primary School",
            "availableVacancies": 150,
            "phase2aVacancies": 59,
            "phase2aApplicants": 4,
            "phase2aBallotStatus": 0,
            "phase2aBallotChance": -1,
            "phase2bVacancies": 38,
            "phase2bApplicants": 0,
            "phase2bBallotStatus": 0,
            "phase2bBallotChance": -1,
            "phase2cVacancies": 115,
            "phase2cApplicants": 27,
            "phase2cBallotStatus": 0,
            "phase2cBallotChance": -1,
            "phase2csVacancies": 88,
            "phase2csApplicants": 21,
            "phase2csBallotStatus": 0,
            "phase2csBallotChance": -1
        },
        {
            "code": 5022,
            "name": "Geylang Methodist School (Primary)",
            "availableVacancies": 270,
            "phase2aVacancies": 108,
            "phase2aApplicants": 32,
            "phase2aBallotStatus": 0,
            "phase2aBallotChance": -1,
            "phase2bVacancies": 45,
            "phase2bApplicants": 4,
            "phase2bBallotStatus": 0,
            "phase2bBallotChance": -1,
            "phase2cVacancies": 132,
            "phase2cApplicants": 134,
            "phase2cBallotStatus": 6,
            "phase2cBallotChance": 0.3333333333,
            "phase2csVacancies": 0,
            "phase2csApplicants": 0,
            "phase2csBallotStatus": 7,
            "phase2csBallotChance": -1
        },
        {
            "code": 1222,
            "name": "Gongshang Primary School",
            "availableVacancies": 220,
            "phase2aVacancies": 46,
            "phase2aApplicants": 163,
            "phase2aBallotStatus": 1,
            "phase2aBallotChance": 0.5679012346,
            "phase2bVacancies": 20,
            "phase2bApplicants": 16,
            "phase2bBallotStatus": 0,
            "phase2bBallotChance": -1,
            "phase2cVacancies": 44,
            "phase2cApplicants": 107,
            "phase2cBallotStatus": 0,
            "phase2cBallotChance": 0.5714285714,
            "phase2csVacancies": 0,
            "phase2csApplicants": 0,
            "phase2csBallotStatus": 7,
            "phase2csBallotChance": -1
        },
        {
            "code": 1251,
            "name": "Greendale Primary School",
            "availableVacancies": 280,
            "phase2aVacancies": 152,
            "phase2aApplicants": 22,
            "phase2aBallotStatus": 0,
            "phase2aBallotChance": -1,
            "phase2bVacancies": 63,
            "phase2bApplicants": 0,
            "phase2bBallotStatus": 0,
            "phase2bBallotChance": -1,
            "phase2cVacancies": 190,
            "phase2cApplicants": 23,
            "phase2cBallotStatus": 0,
            "phase2cBallotChance": -1,
            "phase2csVacancies": 167,
            "phase2csApplicants": 17,
            "phase2csBallotStatus": 0,
            "phase2csBallotChance": -1
        },
        {
            "code": 1245,
            "name": "Greenridge Primary School",
            "availableVacancies": 180,
            "phase2aVacancies": 53,
            "phase2aApplicants": 9,
            "phase2aBallotStatus": 0,
            "phase2aBallotChance": -1,
            "phase2bVacancies": 35,
            "phase2bApplicants": 1,
            "phase2bBallotStatus": 0,
            "phase2bBallotChance": -1,
            "phase2cVacancies": 103,
            "phase2cApplicants": 19,
            "phase2cBallotStatus": 0,
            "phase2cBallotChance": -1,
            "phase2csVacancies": 84,
            "phase2csApplicants": 7,
            "phase2csBallotStatus": 0,
            "phase2csBallotChance": -1
        },
        {
            "code": 1765,
            "name": "Greenwood Primary School",
            "availableVacancies": 240,
            "phase2aVacancies": 82,
            "phase2aApplicants": 16,
            "phase2aBallotStatus": 0,
            "phase2aBallotChance": -1,
            "phase2bVacancies": 42,
            "phase2bApplicants": 3,
            "phase2bBallotStatus": 0,
            "phase2bBallotChance": -1,
            "phase2cVacancies": 123,
            "phase2cApplicants": 89,
            "phase2cBallotStatus": 0,
            "phase2cBallotChance": -1,
            "phase2csVacancies": 34,
            "phase2csApplicants": 33,
            "phase2csBallotStatus": 0,
            "phase2csBallotChance": -1
        },
        {
            "code": 1038,
            "name": "Haig Girls' School",
            "availableVacancies": 190,
            "phase2aVacancies": 79,
            "phase2aApplicants": 24,
            "phase2aBallotStatus": 0,
            "phase2aBallotChance": -1,
            "phase2bVacancies": 38,
            "phase2bApplicants": 18,
            "phase2bBallotStatus": 0,
            "phase2bBallotChance": -1,
            "phase2cVacancies": 97,
            "phase2cApplicants": 108,
            "phase2cBallotStatus": 4,
            "phase2cBallotChance": 0.5,
            "phase2csVacancies": 0,
            "phase2csApplicants": 0,
            "phase2csBallotStatus": 7,
            "phase2csBallotChance": -1
        },
        {
            "code": 1121,
            "name": "Henry Park Primary School",
            "availableVacancies": 300,
            "phase2aVacancies": 109,
            "phase2aApplicants": 109,
            "phase2aBallotStatus": 0,
            "phase2aBallotChance": -1,
            "phase2bVacancies": 20,
            "phase2bApplicants": 23,
            "phase2bBallotStatus": 1,
            "phase2bBallotChance": 0.9523809524,
            "phase2cVacancies": 44,
            "phase2cApplicants": 64,
            "phase2cBallotStatus": 1,
            "phase2cBallotChance": 0.8301886792,
            "phase2csVacancies": 0,
            "phase2csApplicants": 0,
            "phase2csBallotStatus": 7,
            "phase2csBallotChance": -1
        },
        {
            "code": 5634,
            "name": "Holy Innocents' Primary School",
            "availableVacancies": 270,
            "phase2aVacancies": 103,
            "phase2aApplicants": 115,
            "phase2aBallotStatus": 3,
            "phase2aBallotChance": 0.6129032258,
            "phase2bVacancies": 20,
            "phase2bApplicants": 53,
            "phase2bBallotStatus": 1,
            "phase2bBallotChance": 0.487804878,
            "phase2cVacancies": 40,
            "phase2cApplicants": 115,
            "phase2cBallotStatus": 1,
            "phase2cBallotChance": 0.412371134,
            "phase2csVacancies": 0,
            "phase2csApplicants": 0,
            "phase2csBallotStatus": 7,
            "phase2csBallotChance": -1
        },
        {
            "code": 5626,
            "name": "Hong Wen School",
            "availableVacancies": 210,
            "phase2aVacancies": 69,
            "phase2aApplicants": 34,
            "phase2aBallotStatus": 0,
            "phase2aBallotChance": -1,
            "phase2bVacancies": 32,
            "phase2bApplicants": 30,
            "phase2bBallotStatus": 0,
            "phase2bBallotChance": -1,
            "phase2cVacancies": 69,
            "phase2cApplicants": 151,
            "phase2cBallotStatus": 1,
            "phase2cBallotChance": 0.5,
            "phase2csVacancies": 0,
            "phase2csApplicants": 0,
            "phase2csBallotStatus": 7,
            "phase2csBallotChance": -1
        },
        {
            "code": 1255,
            "name": "Horizon Primary School",
            "availableVacancies": 240,
            "phase2aVacancies": 77,
            "phase2aApplicants": 105,
            "phase2aBallotStatus": 0.9625,
            "phase2aBallotChance": -1,
            "phase2bVacancies": 20,
            "phase2bApplicants": 16,
            "phase2bBallotStatus": 0,
            "phase2bBallotChance": -1,
            "phase2cVacancies": 44,
            "phase2cApplicants": 81,
            "phase2cBallotStatus": 1,
            "phase2cBallotChance": 0.602739726,
            "phase2csVacancies": 0,
            "phase2csApplicants": 0,
            "phase2csBallotStatus": 7,
            "phase2csBallotChance": -1
        },
        {
            "code": 1763,
            "name": "Hougang Primary School",
            "availableVacancies": 190,
            "phase2aVacancies": 54,
            "phase2aApplicants": 22,
            "phase2aBallotStatus": 0,
            "phase2aBallotChance": -1,
            "phase2bVacancies": 31,
            "phase2bApplicants": 17,
            "phase2bBallotStatus": 0,
            "phase2bBallotChance": -1,
            "phase2cVacancies": 76,
            "phase2cApplicants": 98,
            "phase2cBallotStatus": 1,
            "phase2cBallotChance": 0.8260869565,
            "phase2csVacancies": 0,
            "phase2csApplicants": 0,
            "phase2csBallotStatus": 7,
            "phase2csBallotChance": -1
        },
        {
            "code": 1223,
            "name": "Huamin Primary School",
            "availableVacancies": 240,
            "phase2aVacancies": 79,
            "phase2aApplicants": 90,
            "phase2aBallotStatus": 2,
            "phase2aBallotChance": 0.5,
            "phase2bVacancies": 20,
            "phase2bApplicants": 1,
            "phase2bBallotStatus": 0,
            "phase2bBallotChance": -1,
            "phase2cVacancies": 61,
            "phase2cApplicants": 95,
            "phase2cBallotStatus": 1,
            "phase2cBallotChance": 0.7261904762,
            "phase2csVacancies": 0,
            "phase2csApplicants": 0,
            "phase2csBallotStatus": 7,
            "phase2csBallotChance": -1
        },
        {
            "code": 1250,
            "name": "Innova Primary School",
            "availableVacancies": 180,
            "phase2aVacancies": 56,
            "phase2aApplicants": 9,
            "phase2aBallotStatus": 0,
            "phase2aBallotChance": -1,
            "phase2bVacancies": 36,
            "phase2bApplicants": 11,
            "phase2bBallotStatus": 0,
            "phase2bBallotChance": -1,
            "phase2cVacancies": 96,
            "phase2cApplicants": 58,
            "phase2cBallotStatus": 0,
            "phase2cBallotChance": -1,
            "phase2csVacancies": 38,
            "phase2csApplicants": 4,
            "phase2csBallotStatus": 0,
            "phase2csBallotChance": -1
        },
        {
            "code": 1207,
            "name": "Jiemin Primary School",
            "availableVacancies": 220,
            "phase2aVacancies": 92,
            "phase2aApplicants": 19,
            "phase2aBallotStatus": 0,
            "phase2aBallotChance": -1,
            "phase2bVacancies": 44,
            "phase2bApplicants": 0,
            "phase2bBallotStatus": 0,
            "phase2bBallotChance": -1,
            "phase2cVacancies": 134,
            "phase2cApplicants": 57,
            "phase2cBallotStatus": 0,
            "phase2cBallotChance": -1,
            "phase2csVacancies": 77,
            "phase2csApplicants": 54,
            "phase2csBallotStatus": 0,
            "phase2csBallotChance": -1
        },
        {
            "code": 1166,
            "name": "Jing Shan Primary School",
            "availableVacancies": 150,
            "phase2aVacancies": 39,
            "phase2aApplicants": 51,
            "phase2aBallotStatus": 2,
            "phase2aBallotChance": 0.4444444444,
            "phase2bVacancies": 20,
            "phase2bApplicants": 1,
            "phase2bBallotStatus": 0,
            "phase2bBallotChance": -1,
            "phase2cVacancies": 61,
            "phase2cApplicants": 62,
            "phase2cBallotStatus": 4,
            "phase2cBallotChance": 1,
            "phase2csVacancies": 0,
            "phase2csApplicants": 0,
            "phase2csBallotStatus": 7,
            "phase2csBallotChance": -1
        },
        {
            "code": 1727,
            "name": "Junyuan Primary School",
            "availableVacancies": 240,
            "phase2aVacancies": 97,
            "phase2aApplicants": 76,
            "phase2aBallotStatus": 0,
            "phase2aBallotChance": -1,
            "phase2bVacancies": 27,
            "phase2bApplicants": 0,
            "phase2bBallotStatus": 0,
            "phase2bBallotChance": -1,
            "phase2cVacancies": 81,
            "phase2cApplicants": 58,
            "phase2cBallotStatus": 0,
            "phase2cBallotChance": -1,
            "phase2csVacancies": 23,
            "phase2csApplicants": 74,
            "phase2csBallotStatus": 1,
            "phase2csBallotChance": 0.5227272727
        },
        {
            "code": 1045,
            "name": "Jurong Primary School",
            "availableVacancies": 220,
            "phase2aVacancies": 101,
            "phase2aApplicants": 37,
            "phase2aBallotStatus": 0,
            "phase2aBallotChance": -1,
            "phase2bVacancies": 41,
            "phase2bApplicants": 0,
            "phase2bBallotStatus": 0,
            "phase2bBallotChance": -1,
            "phase2cVacancies": 125,
            "phase2cApplicants": 73,
            "phase2cBallotStatus": 0,
            "phase2cBallotChance": -1,
            "phase2csVacancies": 52,
            "phase2csApplicants": 72,
            "phase2csBallotStatus": 2,
            "phase2csBallotChance": 0.48
        },
        {
            "code": 1753,
            "name": "Jurong West Primary School",
            "availableVacancies": 180,
            "phase2aVacancies": 63,
            "phase2aApplicants": 65,
            "phase2aBallotStatus": 1,
            "phase2aBallotChance": 0.6666666667,
            "phase2bVacancies": 20,
            "phase2bApplicants": 1,
            "phase2bBallotStatus": 0,
            "phase2bBallotChance": -1,
            "phase2cVacancies": 60,
            "phase2cApplicants": 63,
            "phase2cBallotStatus": 4,
            "phase2cBallotChance": 0.8461538462,
            "phase2csVacancies": 0,
            "phase2csApplicants": 0,
            "phase2csBallotStatus": 7,
            "phase2csBallotChance": -1
        },
        {
            "code": 1238,
            "name": "Keming Primary School",
            "availableVacancies": 240,
            "phase2aVacancies": 80,
            "phase2aApplicants": 51,
            "phase2aBallotStatus": 0,
            "phase2aBallotChance": -1,
            "phase2bVacancies": 30,
            "phase2bApplicants": 8,
            "phase2bBallotStatus": 0,
            "phase2bBallotChance": -1,
            "phase2cVacancies": 82,
            "phase2cApplicants": 138,
            "phase2cBallotStatus": 1,
            "phase2cBallotChance": 0.4555555556,
            "phase2csVacancies": 0,
            "phase2csApplicants": 0,
            "phase2csBallotStatus": 7,
            "phase2csBallotChance": -1
        },
        {
            "code": 5608,
            "name": "Kheng Cheng School",
            "availableVacancies": 240,
            "phase2aVacancies": 109,
            "phase2aApplicants": 47,
            "phase2aBallotStatus": 0,
            "phase2aBallotChance": -1,
            "phase2bVacancies": 41,
            "phase2bApplicants": 1,
            "phase2bBallotStatus": 0,
            "phase2bBallotChance": -1,
            "phase2cVacancies": 121,
            "phase2cApplicants": 110,
            "phase2cBallotStatus": 0,
            "phase2cBallotChance": -1,
            "phase2csVacancies": 11,
            "phase2csApplicants": 28,
            "phase2csBallotStatus": 1,
            "phase2csBallotChance": 0.6111111111
        },
        {
            "code": 5168,
            "name": "Kong Hwa School",
            "availableVacancies": 270,
            "phase2aVacancies": 100,
            "phase2aApplicants": 74,
            "phase2aBallotStatus": 0,
            "phase2aBallotChance": -1,
            "phase2bVacancies": 29,
            "phase2bApplicants": 57,
            "phase2bBallotStatus": 1,
            "phase2bBallotChance": 0.6590909091,
            "phase2cVacancies": 57,
            "phase2cApplicants": 84,
            "phase2cBallotStatus": 1,
            "phase2cBallotChance": 0.8260869565,
            "phase2csVacancies": 0,
            "phase2csApplicants": 0,
            "phase2csBallotStatus": 7,
            "phase2csBallotChance": -1
        },
        {
            "code": 1745,
            "name": "Kranji Primary School",
            "availableVacancies": 120,
            "phase2aVacancies": 25,
            "phase2aApplicants": 25,
            "phase2aBallotStatus": 0,
            "phase2aBallotChance": -1,
            "phase2bVacancies": 20,
            "phase2bApplicants": 0,
            "phase2bBallotStatus": 0,
            "phase2bBallotChance": -1,
            "phase2cVacancies": 60,
            "phase2cApplicants": 21,
            "phase2cBallotStatus": 0,
            "phase2cBallotChance": -1,
            "phase2csVacancies": 39,
            "phase2csApplicants": 16,
            "phase2csBallotStatus": 0,
            "phase2csBallotChance": -1
        },
        {
            "code": 5024,
            "name": "Kuo Chuan Presbyterian Primary School",
            "availableVacancies": 240,
            "phase2aVacancies": 92,
            "phase2aApplicants": 57,
            "phase2aBallotStatus": 0,
            "phase2aBallotChance": -1,
            "phase2bVacancies": 32,
            "phase2bApplicants": 36,
            "phase2bBallotStatus": 3,
            "phase2bBallotChance": 0.3333333333,
            "phase2cVacancies": 67,
            "phase2cApplicants": 76,
            "phase2cBallotStatus": 2,
            "phase2cBallotChance": 0.9375,
            "phase2csVacancies": 0,
            "phase2csApplicants": 0,
            "phase2csBallotStatus": 7,
            "phase2csBallotChance": -1
        }
    ]
}